xgrow/CHANGELOG.md
xgrow/__init__.py
xgrow/_script_xgrow.py
xgrow/_xgrow
xgrow/libapi.py
xgrow/meson.build
xgrow/parseoutput.py
xgrow/py.typed
xgrow/stxg.py
xgrow/tileset.py
xgrow/xcolors.py
xgrow/xgrow.py
xgrow/xgrow_parallel.py
xgrow-20220725.dist-info/METADATA
xgrow-20220725.dist-info/WHEEL
xgrow-20220725.dist-info/entry_points.txt
xgrow-20220725.dist-info/top_level.txt
xgrow-20220725.dist-info/RECORD
