Metadata-Version: 2.1
Name: xgrow
Version: 20220725
Summary: Xgrow in pythonic form
Author: Constantine Evans et al (this version)
Author-email: const@costi.eu
Requires-Dist: pyyaml
Requires-Dist: typing-extensions
Requires-Dist: numpy
Requires-Dist: pandas
Requires-Dist: matplotlib
